cursor_agent_tools/__init__.py
cursor_agent_tools/base.py
cursor_agent_tools/claude_agent.py
cursor_agent_tools/factory.py
cursor_agent_tools/interact.py
cursor_agent_tools/logger.py
cursor_agent_tools/ollama_agent.py
cursor_agent_tools/openai_agent.py
cursor_agent_tools/permissions.py
cursor_agent_tools/agent/__init__.py
cursor_agent_tools/agent/tools/__init__.py
cursor_agent_tools/agent/tools/file_tools.py
cursor_agent_tools/agent/tools/register_tools.py
cursor_agent_tools/agent/tools/search_tools.py
cursor_agent_tools/agent/tools/system_tools.py
cursor_agent_tools/tools/__init__.py
cursor_agent_tools/tools/file_tools.py
cursor_agent_tools/tools/image_tools.py
cursor_agent_tools/tools/register_tools.py
cursor_agent_tools/tools/search_tools.py
cursor_agent_tools/tools/system_tools.py
cursor_agent_tools-0.1.39.dist-info/licenses/LICENSE
cursor_agent_tools-0.1.39.dist-info/METADATA
cursor_agent_tools-0.1.39.dist-info/WHEEL
cursor_agent_tools-0.1.39.dist-info/top_level.txt
cursor_agent_tools-0.1.39.dist-info/RECORD
