Metadata-Version: 2.4
Name: cursor-agent-tools
Version: 0.1.39
Summary: Cursor Agent Tools - A Python-based AI agent that replicates Cursor's coding assistant capabilities
Home-page: https://github.com/civai-technologies/cursor-agent
Author: Nifemi Alpine
Author-email: hello@civai.co
Classifier: Development Status :: 4 - Beta
Classifier: Programming Language :: Python :: 3
Classifier: Programming Language :: Python :: 3.8
Classifier: Programming Language :: Python :: 3.9
Classifier: Programming Language :: Python :: 3.10
Classifier: Programming Language :: Python :: 3.11
Classifier: License :: OSI Approved :: MIT License
Classifier: Operating System :: OS Independent
Classifier: Topic :: Software Development :: Libraries :: Python Modules
Classifier: Topic :: Scientific/Engineering :: Artificial Intelligence
Requires-Python: >=3.8
License-File: LICENSE
Requires-Dist: anthropic>=0.49.0
Requires-Dist: openai>=1.6.1
Requires-Dist: colorama>=0.4.6
Requires-Dist: python-dotenv>=1.0.0
Requires-Dist: typing-extensions>=4.8.0
Requires-Dist: requests>=2.31.0
Requires-Dist: urllib3>=2.0.7
Requires-Dist: httpx>=0.25.0
Requires-Dist: ollama>=0.4.0
Requires-Dist: beautifulsoup4>=4.12.0
Provides-Extra: dev
Requires-Dist: pytest>=7.0.0; extra == "dev"
Requires-Dist: pytest-cov>=4.0.0; extra == "dev"
Requires-Dist: black>=23.0.0; extra == "dev"
Requires-Dist: isort>=5.12.0; extra == "dev"
Requires-Dist: flake8>=6.0.0; extra == "dev"
Requires-Dist: mypy>=1.0.0; extra == "dev"
Requires-Dist: bump2version>=1.0.0; extra == "dev"
Dynamic: author
Dynamic: author-email
Dynamic: classifier
Dynamic: description
Dynamic: description-content-type
Dynamic: home-page
Dynamic: license-file
Dynamic: provides-extra
Dynamic: requires-dist
Dynamic: requires-python
Dynamic: summary
